{
    "intercept": 0.0285,
    "coefs": {
        "0": -0.0414,
        "1": 0.1701,
        "2": -0.1813,
        "3": -0.2779,
        "4": 1.0133,
        "5": 0.4454,
        "6": 0.4913,
        "7": 0.1962,
        "8": 0.0694,
        "9": 0.1698,
        "10": -0.191,
        "11": 0.04,
        "12": 0.1196,
        "13": -0.0312,
        "14": -0.1646,
        "15": 0.2209,
        "16": 0.7418,
        "17": 0.3756,
        "18": 0.3505,
        "19": 0.0987,
        "20": 0.203,
        "21": -0.1013,
        "22": -0.4208,
        "23": -0.1398,
        "24": -0.069,
        "25": 0.0087,
        "26": -0.2756,
        "27": 0.0884,
        "28": 0.0955,
        "29": -0.2234,
        "30": 0.0969,
        "31": 0.0731,
        "32": 0.1665,
        "33": -0.2798,
        "34": -0.4443,
        "35": 0.3076,
        "36": 0.2493,
        "37": -0.2359,
        "38": -0.3642,
        "39": -0.5629,
        "40": 0.6878,
        "41": 0.4543,
        "42": -0.0957,
        "43": -0.1379,
        "44": 0.1579,
        "45": 0.274,
        "46": 0.6156,
        "47": -0.3765,
        "48": -0.0415,
        "49": 0.2592,
        "50": -0.3392,
        "51": 0.4794,
        "52": 0.1693,
        "53": -0.1195,
        "54": 0.1692,
        "55": 0.0254,
        "56": 0.1033,
        "57": 0.2564,
        "58": -0.3989,
        "59": -0.0869,
        "60": 0.4269,
        "61": -0.1741,
        "62": -0.1587,
        "63": -0.1868,
        "64": 0.5179,
        "65": -0.0229,
        "66": -0.1552,
        "67": -0.2537,
        "68": -0.3287,
        "69": -0.4596,
        "70": -0.1097,
        "71": -0.5743,
        "72": 0.7833,
        "73": -0.4526,
        "74": 0.4669,
        "75": 0.0994,
        "76": 0.0581,
        "77": -0.4945,
        "78": -0.2456,
        "79": 0.2062,
        "80": -0.3772,
        "81": 0.298,
        "82": 0.0885,
        "83": 0.1744,
        "84": -0.4714,
        "85": 0.0778,
        "86": 0.3379,
        "87": -0.0441,
        "88": -0.5546,
        "89": -0.0393,
        "90": -0.8574,
        "91": -0.3505,
        "92": -0.7749,
        "93": -0.2493,
        "94": 0.248,
        "95": -0.3631,
        "96": 0.0063,
        "97": 0.1276,
        "98": 0.6962,
        "99": 0.1606,
        "100": -0.0607,
        "101": -0.1978,
        "102": 0.1276,
        "103": 0.1554,
        "104": -0.2868,
        "105": 0.3944,
        "106": 0.1026,
        "107": -0.4075,
        "108": -0.5387,
        "109": 0.2177,
        "110": 0.0678,
        "111": -0.2371,
        "112": 0.1071,
        "113": -0.1162,
        "114": -0.2147,
        "115": 0.4673,
        "116": 0.1575,
        "117": 0.1562,
        "118": -0.1889,
        "119": -0.7101,
        "120": 0.1718,
        "121": -0.2677,
        "122": 0.1041,
        "123": -0.2088,
        "124": 0.3689,
        "125": 0.4898,
        "126": -0.0602,
        "127": -0.1821,
        "128": -0.6902,
        "129": -0.5162,
        "130": -0.4534,
        "131": -0.4313,
        "132": -0.6344,
        "133": 0.0551,
        "134": 0.4914,
        "135": -0.1536,
        "136": 0.4662,
        "137": 0.5239,
        "138": 0.3828,
        "139": 0.308,
        "140": 0.4447,
        "141": -0.2942,
        "142": -0.0603,
        "143": 0.1851,
        "144": 0.1692,
        "145": 0.1788,
        "146": 0.4561,
        "147": -0.1369,
        "148": -0.013,
        "149": 0.1621,
        "150": 0.1158,
        "151": 0.1416,
        "152": 0.0054,
        "153": -0.1302,
        "154": -0.2876,
        "155": -0.4991,
        "156": -0.0524,
        "157": 0.3279,
        "158": -0.3134,
        "159": 0.2003,
        "160": 0.4242,
        "161": -0.4266,
        "162": 0.5296,
        "163": 0.9555,
        "164": 0.1187,
        "165": 0.1475,
        "166": 0.7234,
        "167": 0.0337,
        "168": 0.5611,
        "169": 0.3133,
        "170": 0.5032,
        "171": 0.1553,
        "172": -0.1808,
        "173": -0.0331,
        "174": -0.0697,
        "175": 0.1531,
        "176": 0.5174,
        "177": -0.0327,
        "178": 0.0535,
        "179": -0.1687,
        "180": -0.126,
        "181": -0.3307,
        "182": 0.1976,
        "183": -0.0905,
        "184": -0.2415,
        "185": -0.4528,
        "186": -0.0376,
        "187": 0.1402,
        "188": -0.2614,
        "189": 0.2821,
        "190": 0.1623,
        "191": 0.0238,
        "192": -0.2037,
        "193": 0.2597,
        "194": -0.4514,
        "195": 0.1478,
        "196": -0.0141,
        "197": -0.3029,
        "198": -0.1293,
        "199": 0.353,
        "200": -0.1157,
        "201": -0.3633,
        "202": -0.687,
        "203": 0.1715,
        "204": -0.0519,
        "205": 0.2321,
        "206": 0.3232,
        "207": -0.4758,
        "208": -0.015,
        "209": -0.2349,
        "210": -0.3306,
        "211": 0.0603,
        "212": 1.1723,
        "213": 0.0453,
        "214": 0.1087,
        "215": 0.0068,
        "216": -0.3039,
        "217": -0.2705,
        "218": 0.4541,
        "219": -0.393,
        "220": -0.0025,
        "221": 0.2022,
        "222": 0.2833,
        "223": 0.3799,
        "224": 0.2026,
        "225": -0.7904,
        "226": -0.4847,
        "227": 0.3541,
        "228": -0.2026,
        "229": 0.383,
        "230": 0.2436,
        "231": -0.1289,
        "232": -0.4449,
        "233": 0.4852,
        "234": 0.3164,
        "235": -0.1655,
        "236": 0.0065,
        "237": 0.506,
        "238": 0.1616,
        "239": -0.1642,
        "240": -0.1213,
        "241": -0.0874,
        "242": -0.1912,
        "243": 0.0062,
        "244": -0.2742,
        "245": -0.1294,
        "246": -0.0568,
        "247": -0.3613,
        "248": -0.1109,
        "249": -0.604,
        "250": -0.4656,
        "251": 0.0114,
        "252": 0.137,
        "253": -0.1052,
        "254": -0.3895,
        "255": 0.3712,
        "256": 0.5871,
        "257": 0.5324,
        "258": 0.0375,
        "259": 0.3449,
        "260": -0.4845,
        "261": 0.4957,
        "262": 0.3698,
        "263": 0.8032,
        "264": 0.0505,
        "265": 0.2512,
        "266": -0.609,
        "267": -0.2654,
        "268": 0.1617,
        "269": 0.1132,
        "270": -0.6705,
        "271": -0.115,
        "272": 0.4709,
        "273": 0.4446,
        "274": -0.2168,
        "275": -0.4434,
        "276": 0.2256,
        "277": -0.2586,
        "278": -0.1487,
        "279": -0.5535,
        "280": -0.2051,
        "281": -0.3079,
        "282": 0.2559,
        "283": 0.4295,
        "284": 0.2884,
        "285": -0.3015,
        "286": -0.2934,
        "287": 0.1268,
        "288": -0.4244,
        "289": -0.2646,
        "290": 0.1576,
        "291": -0.3041,
        "292": 0.5105,
        "293": -0.0509,
        "294": 0.2181,
        "295": 0.0465,
        "296": 0.3306,
        "297": -0.195,
        "298": -0.3992,
        "299": -0.1234,
        "300": -0.1918,
        "301": -0.1775,
        "302": 0.3306,
        "303": -0.3053,
        "304": 0.1188,
        "305": 0.1934,
        "306": -0.1247,
        "307": -0.032,
        "308": 0.7239,
        "309": 0.01,
        "310": -0.4572,
        "311": 0.0265,
        "312": -0.8906,
        "313": -0.2108,
        "314": 0.2768,
        "315": 0.5313,
        "316": -0.0947,
        "317": -0.1831,
        "318": 0.0818,
        "319": -0.0173,
        "320": 0.2428,
        "321": 0.2179,
        "322": 0.1476,
        "323": -0.0601,
        "324": 0.0842,
        "325": 0.2801,
        "326": 0.2147,
        "327": -0.2378,
        "328": -0.2387,
        "329": -0.4153,
        "330": -0.1751,
        "331": -0.335,
        "332": 0.2635,
        "333": 0.0532,
        "334": -0.3521,
        "335": 0.1431,
        "336": 0.432,
        "337": 0.1594,
        "338": -0.3143,
        "339": 0.2171,
        "340": 0.4512,
        "341": -0.0762,
        "342": -0.5264,
        "343": -0.6024,
        "344": -0.3165,
        "345": -0.0689,
        "346": 0.0283,
        "347": 0.235,
        "348": -0.1441,
        "349": 0.3413,
        "350": -0.0855,
        "351": -0.0649,
        "352": -0.6981,
        "353": -0.1394,
        "354": -0.356,
        "355": -0.7457,
        "356": -0.1234,
        "357": 0.3138,
        "358": 0.7051,
        "359": -0.5726,
        "360": -0.0833,
        "361": 0.0873,
        "362": 0.5196,
        "363": -0.0763,
        "364": -0.5773,
        "365": 0.2621,
        "366": 0.2275,
        "367": -0.0482,
        "368": -0.3712,
        "369": 0.0353,
        "370": -0.1583,
        "371": 0.6243,
        "372": -0.275,
        "373": -0.1152,
        "374": -0.1737,
        "375": -0.2529,
        "376": 0.3426,
        "377": 0.1917,
        "378": 0.9316,
        "379": 0.1032,
        "380": -0.3816,
        "381": -0.2465,
        "382": 0.4778,
        "383": -0.2412,
        "384": 0.1122,
        "385": -0.2476,
        "386": -0.3633,
        "387": 0.1241,
        "388": -0.0343,
        "389": 0.2693,
        "390": -0.4461,
        "391": 0.4058,
        "392": -0.5796,
        "393": 0.7122,
        "394": -0.0258,
        "395": -0.0214,
        "396": 0.5438,
        "397": -0.7261,
        "398": -0.0101,
        "399": -0.2931,
        "400": -0.2268,
        "401": -0.0522,
        "402": 0.0738,
        "403": -0.2969,
        "404": -0.0067,
        "405": 0.492,
        "406": -0.1734,
        "407": -0.0055,
        "408": 0.2219,
        "409": -0.0257,
        "410": 0.1563,
        "411": -0.5852,
        "412": -0.398,
        "413": -0.2411,
        "414": 0.554,
        "415": -0.0484,
        "416": 0.6259,
        "417": 0.5813,
        "418": -0.2472,
        "419": 0.4072,
        "420": -0.337,
        "421": -0.4892,
        "422": -0.2471,
        "423": 0.155,
        "424": -0.1994,
        "425": -0.0764,
        "426": -0.1376,
        "427": -0.2343,
        "428": -0.6552,
        "429": -0.191,
        "430": -0.5133,
        "431": -0.2487,
        "432": 0.1935,
        "433": -0.2897,
        "434": 0.5671,
        "435": 0.1091,
        "436": -0.0597,
        "437": 0.1357,
        "438": 0.4414,
        "439": 0.1004,
        "440": -0.3128,
        "441": -0.0044,
        "442": 0.0214,
        "443": -0.0677,
        "444": 0.5658,
        "445": 0.0576,
        "446": 0.0758,
        "447": -0.0154,
        "448": 0.2699,
        "449": 0.5153,
        "450": 0.2457,
        "451": 0.6595,
        "452": 0.1852,
        "453": -0.1852,
        "454": -0.1931,
        "455": -0.0479,
        "456": 0.1406,
        "457": -0.6806,
        "458": -0.245,
        "459": -0.2532,
        "460": 0.1222,
        "461": 0.2256,
        "462": 0.2439,
        "463": 0.5356,
        "464": -0.5935,
        "465": -0.2866,
        "466": 0.1328,
        "467": 0.3869,
        "468": -0.1978,
        "469": 0.3928,
        "470": -0.4149,
        "471": -0.2513,
        "472": 0.0936,
        "473": 0.154,
        "474": -0.2918,
        "475": 0.088,
        "476": -0.548,
        "477": -0.1305,
        "478": -0.1024,
        "479": -0.3516,
        "480": 0.0464,
        "481": 0.0064,
        "482": 0.1007,
        "483": 0.0718,
        "484": -0.0779,
        "485": -0.2787,
        "486": -0.2181,
        "487": -0.2275,
        "488": 0.1536,
        "489": -0.208,
        "490": -0.759,
        "491": -0.2028,
        "492": -0.6337,
        "493": -0.2141,
        "494": -0.4038,
        "495": 0.4637,
        "496": 0.1474,
        "497": 0.9855,
        "498": 0.1056,
        "499": -0.0471,
        "500": -0.2298,
        "501": 0.1561,
        "502": 0.0207,
        "503": -0.2204,
        "504": 0.4486,
        "505": -0.0444,
        "506": -0.4772,
        "507": 0.282,
        "508": 0.0126,
        "509": 0.0657,
        "510": 0.4532,
        "511": 0.6711,
        "512": -0.2007,
        "513": 0.3083,
        "514": 0.043,
        "515": -0.5585,
        "516": -0.3745,
        "517": -0.1174,
        "518": 0.0897,
        "519": 0.5458,
        "520": 0.181,
        "521": -0.1438,
        "522": 0.126,
        "523": -0.0964,
        "524": -0.1566,
        "525": -0.0668,
        "526": 0.2382,
        "527": 0.2041,
        "528": -0.2764,
        "529": 0.2203,
        "530": -0.4522,
        "531": 0.1802,
        "532": -0.0779,
        "533": -0.4176,
        "534": -0.2066,
        "535": -0.1619,
        "536": -0.1176,
        "537": -0.4644,
        "538": 0.7072,
        "539": -0.056,
        "540": -0.0393,
        "541": 0.3435,
        "542": -0.1679,
        "543": -0.8469,
        "544": 0.211,
        "545": -0.058,
        "546": -0.293,
        "547": -0.0425,
        "548": -0.1738,
        "549": 0.1878,
        "550": 0.8667,
        "551": -0.2203,
        "552": 0.2645,
        "553": -0.331,
        "554": 0.1317,
        "555": 0.6125,
        "556": 0.1546,
        "557": -0.706,
        "558": 0.6869,
        "559": 0.2325,
        "560": -0.3138,
        "561": 0.0181,
        "562": 0.9882,
        "563": -0.152,
        "564": -0.2784,
        "565": 0.3136,
        "566": -0.4823,
        "567": 0.5597,
        "568": 0.0706,
        "569": 0.4035,
        "570": 0.2693,
        "571": -0.2421,
        "572": -0.282,
        "573": -0.1519,
        "574": 1.1647,
        "575": 0.3425,
        "576": 0.3474,
        "577": 0.5749,
        "578": -0.1532,
        "579": 0.0954,
        "580": -0.8253,
        "581": -0.1917,
        "582": -0.5432,
        "583": 0.8896,
        "584": 0.2683,
        "585": -0.148,
        "586": 0.1187,
        "587": 0.5021,
        "588": 0.0589,
        "589": -0.4809,
        "590": 0.302,
        "591": -0.2252,
        "592": 0.0129,
        "593": 0.2947,
        "594": 0.1385,
        "595": -0.0099,
        "596": 0.2158,
        "597": -0.2685,
        "598": 0.1654,
        "599": -0.0513,
        "600": 0.4711,
        "601": 0.0155,
        "602": -0.2938,
        "603": -0.3987,
        "604": -0.0616,
        "605": 0.4331,
        "606": -0.0094,
        "607": -0.194,
        "608": -0.4625,
        "609": -0.2305,
        "610": -0.1311,
        "611": 0.0787,
        "612": 0.0164,
        "613": -0.1084,
        "614": -0.6268,
        "615": 0.4243,
        "616": -0.1182,
        "617": -0.8135,
        "618": -0.2325,
        "619": 0.1279,
        "620": 0.0553,
        "621": 0.0686,
        "622": -0.2797,
        "623": -0.0375,
        "624": -0.2082,
        "625": 0.6582,
        "626": 0.9242,
        "627": -0.1813,
        "628": -0.3717,
        "629": -0.1652,
        "630": 0.3472,
        "631": -0.1009,
        "632": -0.3206,
        "633": -0.2239,
        "634": 0.0641,
        "635": -0.1409,
        "636": -0.1361,
        "637": -0.2591,
        "638": 0.1015,
        "639": -0.1445,
        "640": 0.037,
        "641": -0.1461,
        "642": 0.0172,
        "643": -0.0565,
        "644": 0.0675,
        "645": 0.3476,
        "646": 0.069,
        "647": -0.2562,
        "648": -0.0754,
        "649": 0.1956,
        "650": 0.2949,
        "651": 0.0468,
        "652": 0.337,
        "653": 0.1907,
        "654": -0.2194,
        "655": 0.0154,
        "656": -0.3299,
        "657": 0.4904,
        "658": 0.0827,
        "659": -0.3925,
        "660": -0.1841,
        "661": 0.0315,
        "662": 0.0983,
        "663": -0.0045,
        "664": 0.0248,
        "665": 0.9345,
        "666": -0.3929,
        "667": -0.3151,
        "668": -0.0999,
        "669": -0.1824,
        "670": -0.1547,
        "671": 0.5282,
        "672": -0.0195,
        "673": -0.021,
        "674": -0.0657,
        "675": 0.0493,
        "676": 0.7267,
        "677": -0.475,
        "678": 0.0435,
        "679": -0.1921,
        "680": 0.0117,
        "681": 0.0893,
        "682": 0.3992,
        "683": 0.3463,
        "684": 0.2666,
        "685": -0.1616,
        "686": 0.2651,
        "687": -0.2199,
        "688": 0.1567,
        "689": 0.0799,
        "690": -0.3826,
        "691": -0.0469,
        "692": 0.256,
        "693": 0.1155,
        "694": -0.769,
        "695": 0.484,
        "696": 0.0961,
        "697": -0.0131,
        "698": -0.0499,
        "699": 0.6497,
        "700": -0.3783,
        "701": -0.037,
        "702": 0.4226,
        "703": 0.5008,
        "704": 0.5958,
        "705": -0.4101,
        "706": -0.2236,
        "707": 0.2746,
        "708": 0.6452,
        "709": -0.0704,
        "710": 0.1998,
        "711": -1.2281,
        "712": 0.0369,
        "713": 0.3524,
        "714": -0.2216,
        "715": 0.192,
        "716": 0.0011,
        "717": -0.3038,
        "718": 0.2319,
        "719": 0.0788,
        "720": -0.6344,
        "721": 0.2748,
        "722": -0.222,
        "723": -0.2414,
        "724": 0.1126,
        "725": 0.3723,
        "726": 0.7936,
        "727": 0.237,
        "728": -0.5269,
        "729": 0.1722,
        "730": 0.0626,
        "731": 0.3726,
        "732": -0.1736,
        "733": 0.4945,
        "734": 0.3621,
        "735": -0.1374,
        "736": -0.1045,
        "737": -0.1137,
        "738": -0.0567,
        "739": -0.1385,
        "740": 0.8659,
        "741": -0.3651,
        "742": 0.0901,
        "743": -0.0443,
        "744": 0.1565,
        "745": 0.1947,
        "746": -0.5593,
        "747": 0.2189,
        "748": 0.0066,
        "749": -0.1961,
        "750": 0.2093,
        "751": -0.2948,
        "752": 0.0844,
        "753": -0.0269,
        "754": 0.0729,
        "755": -0.2979,
        "756": -0.3941,
        "757": 0.2327,
        "758": 0.6447,
        "759": -0.5417,
        "760": -0.0268,
        "761": 0.6143,
        "762": -0.4412,
        "763": 0.0235,
        "764": -0.242,
        "765": 0.279,
        "766": 0.1984,
        "767": -0.3852,
        "768": -0.2257,
        "769": 0.278,
        "770": 0.1735,
        "771": -0.4603,
        "772": 0.1829,
        "773": -0.4489,
        "774": -0.2115,
        "775": 0.1588,
        "776": 0.1654,
        "777": -0.0361,
        "778": 0.2212,
        "779": 0.0996,
        "780": -0.3189,
        "781": 0.3248,
        "782": -0.0405,
        "783": -0.3059,
        "784": -0.0872,
        "785": -0.0155,
        "786": 0.006,
        "787": 0.2595,
        "788": -0.1278,
        "789": 0.2951,
        "790": 0.435,
        "791": -0.4246,
        "792": -0.084,
        "793": 0.3615,
        "794": 0.4247,
        "795": 0.0236,
        "796": 0.2117,
        "797": -0.3115,
        "798": 0.0764,
        "799": 0.4672,
        "800": -0.1421,
        "801": 0.2646,
        "802": 0.5461,
        "803": 0.5219,
        "804": -0.3037,
        "805": 0.4867,
        "806": -0.1445,
        "807": -0.1874,
        "808": -0.1199,
        "809": -0.1567,
        "810": 0.0448,
        "811": 0.3042,
        "812": -0.3856,
        "813": 0.0271,
        "814": -0.186,
        "815": -0.0814,
        "816": 0.1628,
        "817": -0.0059,
        "818": -0.2551,
        "819": -0.126,
        "820": -0.0594,
        "821": -0.6113,
        "822": 0.5571,
        "823": -0.384,
        "824": 0.1145,
        "825": 0.4815,
        "826": -0.2435,
        "827": 0.2266,
        "828": -0.0262,
        "829": -0.2094,
        "830": 0.3385,
        "831": 0.3518,
        "832": -0.1811,
        "833": -0.4588,
        "834": 0.1659,
        "835": 0.3932,
        "836": 0.0818,
        "837": 0.0799,
        "838": -0.3936,
        "839": -0.1113,
        "840": 0.1296,
        "841": -0.0741,
        "842": -0.1934,
        "843": 0.3927,
        "844": 0.0814,
        "845": -0.3891,
        "846": -0.8059,
        "847": 0.2551,
        "848": -0.1959,
        "849": 0.0657,
        "850": -0.0676,
        "851": 0.272,
        "852": 0.4088,
        "853": -0.0717,
        "854": -0.3969,
        "855": -0.0348,
        "856": 0.4369,
        "857": -0.2035,
        "858": 0.2925,
        "859": 0.3829,
        "860": 0.357,
        "861": 0.4145,
        "862": -0.4639,
        "863": 0.463,
        "864": -0.2114,
        "865": 0.0922,
        "866": 0.1265,
        "867": -0.0628,
        "868": -0.2428,
        "869": 0.1503,
        "870": 0.1424,
        "871": -0.0412,
        "872": -0.0204,
        "873": 0.515,
        "874": -0.3883,
        "875": -0.2041,
        "876": -0.041,
        "877": 0.0101,
        "878": 0.1332,
        "879": 0.0675,
        "880": -0.1632,
        "881": 0.1436,
        "882": 0.1515,
        "883": 0.7371,
        "884": -0.038,
        "885": -0.1374,
        "886": 0.2125,
        "887": -0.519,
        "888": 0.4359,
        "889": 0.4356,
        "890": -0.0233,
        "891": 0.3616,
        "892": 0.2704,
        "893": 0.1637,
        "894": 0.2901,
        "895": -0.2819,
        "896": -0.0977,
        "897": -0.1426,
        "898": 0.0464,
        "899": 0.4579,
        "900": -0.5554,
        "901": -0.1581,
        "902": 0.0929,
        "903": 0.3435,
        "904": -0.4929,
        "905": 0.6624,
        "906": -0.3046,
        "907": -0.7895,
        "908": 0.3061,
        "909": -0.2123,
        "910": 0.2319,
        "911": -0.2263,
        "912": 0.1659,
        "913": 0.3969,
        "914": 0.8541,
        "915": -0.2162,
        "916": 0.3023,
        "917": -0.1211,
        "918": 0.7996,
        "919": -0.3903,
        "920": 0.2983,
        "921": 0.7607,
        "922": -0.3189,
        "923": -0.3032,
        "924": -0.5671,
        "925": 0.3032,
        "926": 0.4445,
        "927": 0.3142,
        "928": 0.1754,
        "929": -0.2276,
        "930": -0.0026,
        "931": -0.5293,
        "932": -0.0714,
        "933": 0.528,
        "934": -0.5652,
        "935": 0.3343,
        "936": 0.0961,
        "937": 0.3813,
        "938": -0.4066,
        "939": -0.8262,
        "940": -0.4691,
        "941": 0.3476,
        "942": -0.5002,
        "943": -0.3077,
        "944": -0.5361,
        "945": -0.0478,
        "946": -0.088,
        "947": -0.1088,
        "948": 0.1261,
        "949": 0.4065,
        "950": 0.1811,
        "951": 0.0397,
        "952": 0.6664,
        "953": -0.3303,
        "954": -0.3834,
        "955": 0.0226,
        "956": -0.3575,
        "957": 0.4764,
        "958": -0.7908,
        "959": -0.2096,
        "960": 0.4688,
        "961": 0.1779,
        "962": -0.1074,
        "963": 0.1065,
        "964": -0.3647,
        "965": -0.177,
        "966": 0.1744,
        "967": 0.2257,
        "968": 0.5149,
        "969": 0.4642,
        "970": -0.4137,
        "971": -0.5622,
        "972": -0.508,
        "973": -0.1206,
        "974": 0.1142,
        "975": 0.3149,
        "976": 0.1873,
        "977": -0.322,
        "978": -0.0482,
        "979": -0.3631,
        "980": 0.0553,
        "981": 0.0932,
        "982": -0.2688,
        "983": -0.1695,
        "984": -0.1583,
        "985": 0.5873,
        "986": -0.07,
        "987": -0.751,
        "988": -0.0534,
        "989": 0.1311,
        "990": 0.2546,
        "991": -0.1215,
        "992": 0.0389,
        "993": -0.2453,
        "994": 0.9073,
        "995": 0.04,
        "996": -0.3382,
        "997": -0.4843,
        "998": 0.3816,
        "999": 0.5379,
        "1000": -0.1427,
        "1001": 0.194,
        "1002": -0.012,
        "1003": -0.353,
        "1004": -1.2461,
        "1005": 0.1218,
        "1006": 0.1099,
        "1007": 0.1221,
        "1008": 0.8068,
        "1009": -0.4534,
        "1010": -0.1215,
        "1011": 0.138,
        "1012": 0.1434,
        "1013": 0.6026,
        "1014": -0.2985,
        "1015": -0.7529,
        "1016": -0.9274,
        "1017": -0.0333,
        "1018": 0.253,
        "1019": 0.0922,
        "1020": 0.0681,
        "1021": -0.0536,
        "1022": -0.1294,
        "1023": -0.4042,
        "1024": -0.14,
        "1025": 0.4935,
        "1026": -0.2036,
        "1027": 0.7199,
        "1028": -0.2433,
        "1029": 0.5298,
        "1030": 0.2117,
        "1031": 0.04,
        "1032": -0.3366,
        "1033": -0.5795,
        "1034": 0.326,
        "1035": 0.3615,
        "1036": -0.007,
        "1037": 0.1389,
        "1038": 0.1109,
        "1039": -0.1145,
        "1040": -0.0392,
        "1041": 0.2871,
        "1042": 0.5311,
        "1043": -0.1415,
        "1044": -0.3397,
        "1045": 0.1964,
        "1046": 0.5415,
        "1047": -0.5907,
        "1048": -0.0447,
        "1049": -0.2167,
        "1050": -0.4833,
        "1051": 0.1712,
        "1052": -0.0767,
        "1053": -0.2688,
        "1054": -0.4148,
        "1055": 0.925,
        "1056": -0.5097,
        "1057": -0.3474,
        "1058": -0.4161,
        "1059": 0.0468,
        "1060": 0.3846,
        "1061": -0.5122,
        "1062": 0.0303,
        "1063": -0.2317,
        "1064": -0.8954,
        "1065": -0.3747,
        "1066": 0.1156,
        "1067": 0.4334,
        "1068": 0.1724,
        "1069": -0.3893,
        "1070": 0.0871,
        "1071": 0.0547,
        "1072": 0.0947,
        "1073": 0.1615,
        "1074": 0.0927,
        "1075": -0.0189,
        "1076": 0.4802,
        "1077": -0.3204,
        "1078": 0.0543,
        "1079": 0.0641,
        "1080": -0.765,
        "1081": -0.0476,
        "1082": 0.5677,
        "1083": 0.2055,
        "1084": 0.352,
        "1085": -0.1077,
        "1086": -0.0709,
        "1087": 0.0067,
        "1088": 0.2495,
        "1089": -0.1806,
        "1090": 0.363,
        "1091": -0.4345,
        "1092": 0.0391,
        "1093": -0.4492,
        "1094": 0.4751,
        "1095": -0.3937,
        "1096": -0.0837,
        "1097": 0.1001,
        "1098": -0.1912,
        "1099": 0.4769,
        "1100": -0.0618,
        "1101": 0.0914,
        "1102": -0.3581,
        "1103": 0.0343,
        "1104": 0.4179,
        "1105": -0.0318,
        "1106": -0.0817,
        "1107": -0.4251,
        "1108": 0.0389,
        "1109": -0.1941,
        "1110": 0.4051,
        "1111": -0.5111,
        "1112": 0.1825,
        "1113": -0.2582,
        "1114": -0.2867,
        "1115": 0.1687,
        "1116": 0.1187,
        "1117": -0.3639,
        "1118": -0.1633,
        "1119": 0.0518,
        "1120": -0.1655,
        "1121": 0.073,
        "1122": -0.2198,
        "1123": 0.0147,
        "1124": 0.2499,
        "1125": -0.1224,
        "1126": 0.0782,
        "1127": -0.1571,
        "1128": 0.5677,
        "1129": -0.3145,
        "1130": -0.2625,
        "1131": -1.0402,
        "1132": -0.2713,
        "1133": 0.3186,
        "1134": -0.1512,
        "1135": -0.9215,
        "1136": -0.1523,
        "1137": -0.4754,
        "1138": 0.1813,
        "1139": 0.1786,
        "1140": 0.3686,
        "1141": -0.5805,
        "1142": -0.0037,
        "1143": -0.0662,
        "1144": 0.2176,
        "1145": 0.0931,
        "1146": 0.3066,
        "1147": -0.2608,
        "1148": 0.0375,
        "1149": 0.1153,
        "1150": 0.5245,
        "1151": 0.1335,
        "1152": -0.2359,
        "1153": -0.1707,
        "1154": -0.0865,
        "1155": 0.3318,
        "1156": 0.1319,
        "1157": -0.4688,
        "1158": 0.0608,
        "1159": 0.0565,
        "1160": -0.0672,
        "1161": -0.1383,
        "1162": 0.0982,
        "1163": 0.2834,
        "1164": 0.5136,
        "1165": -0.0017,
        "1166": -0.402,
        "1167": -0.0317,
        "1168": 0.0888,
        "1169": -0.1067,
        "1170": 0.1512,
        "1171": -0.3858,
        "1172": -0.1165,
        "1173": 0.2052,
        "1174": -0.2162,
        "1175": -0.6738,
        "1176": -0.2024,
        "1177": -0.6374,
        "1178": 0.0876,
        "1179": 0.2809,
        "1180": -0.071,
        "1181": -0.3826,
        "1182": 0.4213,
        "1183": 0.5893,
        "1184": 0.2286,
        "1185": 0.3271,
        "1186": 0.3077,
        "1187": 0.3129,
        "1188": -0.3015,
        "1189": 0.2813,
        "1190": 0.2309,
        "1191": -0.041,
        "1192": -0.2214,
        "1193": -0.43,
        "1194": 0.0256,
        "1195": -0.191,
        "1196": -0.0279,
        "1197": 0.0886,
        "1198": -0.289,
        "1199": -0.2682,
        "1200": -0.6152,
        "1201": 0.1114,
        "1202": -0.5313,
        "1203": -0.3919,
        "1204": 0.0419,
        "1205": 0.1084,
        "1206": -0.8053,
        "1207": -0.006,
        "1208": -0.2607,
        "1209": -0.3065,
        "1210": -0.1442,
        "1211": -0.0561,
        "1212": -0.2125,
        "1213": -0.1048,
        "1214": -0.0244,
        "1215": -0.1903,
        "1216": -0.1968,
        "1217": 0.1088,
        "1218": -0.4293,
        "1219": -0.5265,
        "1220": 0.3404,
        "1221": 0.6368,
        "1222": 0.0838,
        "1223": -0.0631,
        "1224": 0.055,
        "1225": -0.1144,
        "1226": 0.0277,
        "1227": 0.2484,
        "1228": -0.3778,
        "1229": 0.1183,
        "1230": -0.0528,
        "1231": -0.2415,
        "1232": 0.4072,
        "1233": -0.3961,
        "1234": 0.2745,
        "1235": 0.171,
        "1236": -0.4441,
        "1237": -0.1953,
        "1238": 0.2632,
        "1239": 0.113,
        "1240": 0.1889,
        "1241": -0.273,
        "1242": 0.6053,
        "1243": -0.4223,
        "1244": 0.3364,
        "1245": -0.1113,
        "1246": -0.7517,
        "1247": -0.2498,
        "1248": 0.1225,
        "1249": 0.0465,
        "1250": -0.4509,
        "1251": 0.6976,
        "1252": -0.3379,
        "1253": 0.5106,
        "1254": -0.5994,
        "1255": 0.2972,
        "1256": -0.4422,
        "1257": 0.5625,
        "1258": -0.0568,
        "1259": 0.369,
        "1260": -0.6207,
        "1261": -0.5563,
        "1262": 0.0635,
        "1263": 0.2203,
        "1264": -0.9947,
        "1265": 0.1846,
        "1266": 0.0333,
        "1267": 0.4728,
        "1268": -0.0811,
        "1269": 0.2438,
        "1270": 0.1457,
        "1271": 0.3269,
        "1272": -0.068,
        "1273": -0.3366,
        "1274": -0.1932,
        "1275": 0.3722,
        "1276": -0.1807,
        "1277": 0.3324,
        "1278": 0.2268,
        "1279": 0.1019,
        "1280": -0.0339,
        "1281": 0.0465,
        "1282": 0.3865,
        "1283": -0.0754,
        "1284": -0.1936,
        "1285": 0.5776,
        "1286": -0.1805,
        "1287": 0.2561,
        "1288": 0.4521,
        "1289": -0.5462,
        "1290": 0.1428,
        "1291": 0.1116,
        "1292": -0.2149,
        "1293": -0.3358,
        "1294": 0.2402,
        "1295": 0.2588,
        "1296": 0.3908,
        "1297": 0.448,
        "1298": 0.0764,
        "1299": -0.035,
        "1300": 0.0905,
        "1301": 0.2418,
        "1302": -0.102,
        "1303": 0.1672,
        "1304": -0.2539,
        "1305": -0.5208,
        "1306": -0.8322,
        "1307": 0.1401,
        "1308": 0.394,
        "1309": 0.0687,
        "1310": -0.0457,
        "1311": 1.0699,
        "1312": -0.1456,
        "1313": -1.0376,
        "1314": -0.3045,
        "1315": 0.029,
        "1316": 0.0252,
        "1317": 0.2188,
        "1318": 0.3648,
        "1319": 0.4104,
        "1320": -0.5144,
        "1321": -0.1991,
        "1322": 0.1942,
        "1323": 0.2191,
        "1324": -0.5288,
        "1325": -0.3364,
        "1326": 0.4183,
        "1327": -0.1515,
        "1328": 0.2909,
        "1329": -0.3545,
        "1330": -0.4158,
        "1331": 0.1433,
        "1332": -0.0379,
        "1333": -0.5089,
        "1334": -0.031,
        "1335": 0.1349,
        "1336": 0.454,
        "1337": 0.0914,
        "1338": -0.0499,
        "1339": -0.0921,
        "1340": 0.1533,
        "1341": -0.1085,
        "1342": 0.3338,
        "1343": -0.0918,
        "1344": 0.1021,
        "1345": -0.4882,
        "1346": -0.3176,
        "1347": 0.378,
        "1348": 0.243,
        "1349": 0.4631,
        "1350": -0.0058,
        "1351": -0.0459,
        "1352": 0.1465,
        "1353": 0.5225,
        "1354": 0.1009,
        "1355": -0.7239,
        "1356": 0.2516,
        "1357": 0.6652,
        "1358": -0.1524,
        "1359": 0.1002,
        "1360": -0.5163,
        "1361": -0.0527,
        "1362": -0.1965,
        "1363": 0.9804,
        "1364": -0.3092,
        "1365": 0.1965,
        "1366": 0.0462,
        "1367": 0.1642,
        "1368": -0.1326,
        "1369": 0.0501,
        "1370": -0.274,
        "1371": -1.025,
        "1372": 0.0928,
        "1373": 0.1254,
        "1374": -0.0005,
        "1375": -0.1972,
        "1376": -0.413,
        "1377": 0.3983,
        "1378": 0.1724,
        "1379": 0.2098,
        "1380": -0.0556,
        "1381": 0.2023,
        "1382": 0.0603,
        "1383": 0.2279,
        "1384": 0.871,
        "1385": 0.3327,
        "1386": 0.1514,
        "1387": 0.1361,
        "1388": -0.0152,
        "1389": 0.3411,
        "1390": 0.1225,
        "1391": 0.4148,
        "1392": 0.2248,
        "1393": 0.719,
        "1394": -0.978,
        "1395": 0.4469,
        "1396": 0.1054,
        "1397": 0.3257,
        "1398": -0.5038,
        "1399": -0.0211,
        "1400": -0.3384,
        "1401": -0.1173,
        "1402": 0.2111,
        "1403": -0.1307,
        "1404": -0.6214,
        "1405": -0.4793,
        "1406": 0.2216,
        "1407": 0.7947,
        "1408": 0.2792,
        "1409": -0.3366,
        "1410": -0.5053,
        "1411": -0.0719,
        "1412": 0.2089,
        "1413": 0.1679,
        "1414": 0.1758,
        "1415": -0.0457,
        "1416": 0.0847,
        "1417": -0.5091,
        "1418": -0.1124,
        "1419": -0.6813,
        "1420": 0.4742,
        "1421": -0.0771,
        "1422": -0.1872,
        "1423": -0.3916,
        "1424": -0.042,
        "1425": -0.0949,
        "1426": 0.2687,
        "1427": 0.0781,
        "1428": 0.0873,
        "1429": -0.4231,
        "1430": 0.3451,
        "1431": -0.2662,
        "1432": 0.104,
        "1433": -0.1243,
        "1434": -0.1439,
        "1435": 0.2102,
        "1436": 0.0309,
        "1437": 0.3873,
        "1438": 0.8287,
        "1439": 0.1807,
        "1440": -0.1374,
        "1441": -0.1543,
        "1442": 0.3241,
        "1443": 0.1272,
        "1444": -0.0203,
        "1445": 0.0138,
        "1446": 0.34,
        "1447": -0.3181,
        "1448": -0.4713,
        "1449": -0.0366,
        "1450": 0.3786,
        "1451": -0.1581,
        "1452": -0.1679,
        "1453": -0.0803,
        "1454": -0.7704,
        "1455": 0.1069,
        "1456": -0.6708,
        "1457": 0.1277,
        "1458": -0.0568,
        "1459": -0.1594,
        "1460": 0.1366,
        "1461": 0.2278,
        "1462": -1.1962,
        "1463": -0.1962,
        "1464": 0.1496,
        "1465": -0.0922,
        "1466": -0.038,
        "1467": -0.0006,
        "1468": -0.0625,
        "1469": -0.3496,
        "1470": 0.6389,
        "1471": 0.1874,
        "1472": 0.0002,
        "1473": 0.161,
        "1474": -0.4121,
        "1475": -0.0504,
        "1476": -0.345,
        "1477": 0.0769,
        "1478": 0.324,
        "1479": 0.0566,
        "1480": -0.2279,
        "1481": -0.0729,
        "1482": 0.0249,
        "1483": -0.3296,
        "1484": -0.6858,
        "1485": 0.2454,
        "1486": 0.5274,
        "1487": -0.0331,
        "1488": -0.1131,
        "1489": -0.0672,
        "1490": 0.3437,
        "1491": 0.0278,
        "1492": 0.3416,
        "1493": 0.2814,
        "1494": -0.6283,
        "1495": 0.5739,
        "1496": -0.04,
        "1497": -0.1375,
        "1498": 0.4322,
        "1499": 0.3836,
        "1500": -0.1662,
        "1501": -0.4,
        "1502": -0.0124,
        "1503": -0.1343,
        "1504": -0.2231,
        "1505": 0.0234,
        "1506": 0.1021,
        "1507": 0.8243,
        "1508": 0.9177,
        "1509": -0.2661,
        "1510": -0.2309,
        "1511": -0.1707,
        "1512": 0.0248,
        "1513": -0.2184,
        "1514": 0.2774,
        "1515": 0.2093,
        "1516": 0.7264,
        "1517": 0.0355,
        "1518": -0.5115,
        "1519": -0.231,
        "1520": -0.3128,
        "1521": -0.3043,
        "1522": -0.344,
        "1523": 0.2514,
        "1524": 0.0146,
        "1525": 0.06,
        "1526": -0.4268,
        "1527": 0.1879,
        "1528": -0.3491,
        "1529": 0.3333,
        "1530": -0.158,
        "1531": 0.029,
        "1532": 0.8843,
        "1533": -0.3365,
        "1534": -0.3492,
        "1535": -0.3102
    }
}